{
    "name": "Mag Innovision LT916S 900P 19\" Flat Panel for Parts | eBay",
    "aspect_ratio": "4:3",
    "brightness": "300 cd/m²",
    "condition": "For parts or not working: An item that does not function as intended and is not fully operational. This includes items that\nare defective in ways that render them difficult to use, items that require service or repair, or items missing essential components. See the seller’s listing for full details.\nSee all condition definitions- opens in a new window or tab\n... Read moreabout the condition\nBrand:\nMAG Innovision",
    "contrast_ratio": "500",
    "model": "LT917S",
    "response_time": "8 ms",
    "screen_size": "19\"",
    "upc": "789806003643"
}