{
    "name": "Samsung SyncMaster S27A850D 27 LED LCD Monitor 16 9 5ms TAA Yes 2560 729507817149 | eBay",
    "aspect_ratio": "16:9",
    "backlight_technology": "LED",
    "manufacturer": "Samsung",
    "brightness": "300 Nit",
    "condition": "New: A brand-new, unused, unopened, undamaged item in its original packaging (where packaging is\napplicable). Packaging should be the same as what is found in a retail store, unless the item is handmade or was packaged by the manufacturer in non-retail packaging, such as an unprinted box or plastic bag. See the seller's listing for full details.\nSee all condition definitions- opens in a new window or tab\n... Read moreabout the condition\nBrand:\nSamsung",
    "contrast_ratio": "1,000:1",
    "dimensions": "25.3\"",
    "displayport": "Yes",
    "certifications": "Energy Star,TCO Displays 5.0",
    "model": "850",
    "description": "LCD Monitor",
    "response_time": "5 ms",
    "screen_size": "27\"",
    "power_consumption": "1 W",
    "upc": "729507817149",
    "weight": "14.55 lb"
}