{
    "name": "Samsung SyncMaster B2240 22'' LCD VGA DVI Monitor Refurbished Tested incl Cables 0729507813851 | eBay",
    "aspect_ratio": "16:9",
    "condition": "Manufacturer refurbished: An item that has been professionally restored to working order by a manufacturer or\nmanufacturer-approved vendor. This means the product has been inspected, cleaned, and repaired to meet manufacturer specifications and is in excellent condition. This item may or may not be in the original packaging. See the seller’s listing for full details.\nSee all condition definitions- opens in a new window or tab\n... Read moreabout the condition\nBrand:\nSamsung",
    "contrast_ratio": "50000, 1000",
    "model": "LS22CBDMBV/ZA",
    "response_time": "5 ms",
    "screen_size": "22\"",
    "upc": "0729507813851"
}