{
    "name": "Compare prices for Asus VS198D monitor, Asus VS 198D reviews - ShopMania",
    "aspect_ratio": "16:10",
    "backlight_technology": "LED",
    "manufacturer": "Asus",
    "brightness": "250",
    "category": "Monitors",
    "contrast_ratio": "1000:1",
    "display_type": "LED",
    "pixel_pitch": "0 mm",
    "ean": "0610839379088, 4719543380819",
    "power_consumption": "25 W (less than 78%)",
    "description": "Asus VS198D",
    "resolution": "1440x900",
    "response_time": "5 ms",
    "upc": "610839379088",
    "viewing_angle": "170/160",
    "weight": "5.95 lb"
}