{
    "name": "Compare prices for Asus VE248Q monitor, Asus VE 248Q reviews - ShopMania",
    "aspect_ratio": "16:9",
    "backlight_technology": "LED",
    "manufacturer": "Asus",
    "brightness": "250",
    "category": "Monitors",
    "dimensions": "56.90 cm",
    "display_type": "LCD",
    "pixel_pitch": "0 mm",
    "ean": "0610839386246",
    "power_consumption": "35 W (less than 56%)",
    "description": "Asus VE248Q",
    "resolution": "1920x1080 (more than 61%)",
    "response_time": "2 ms (less than 89%)",
    "upc": "610839386246",
    "viewing_angle": "170/160"
}