{
    "name": "HP VM633A8#ABA - Vology",
    "aspect_ratio": "Widescreen - 16:10",
    "brightness": "400 cd/m2",
    "contrast_ratio": "1000:1 / 3000:1 (dynamic)",
    "display_type": "LCD monitor / TFT active matrix",
    "height_adjustable": "3.9 in",
    "operating_temperature": "20 - 80%",
    "pixel_pitch": "0.27 mm",
    "power_consumption": "95 Watt",
    "response_time": "12 ms (On/Off); 7 ms (gray-to-gray)",
    "tilt_angle": "35",
    "voltage": "AC 120/230 V ( 50/60 Hz )",
    "weight": "18.7 lbs"
}