{
    "name": "AOC m2870Vq 28\" Widescreen MVA LED Black Multimedia Monitor (1920 x 1080/5ms/VGA/DVI/HDMI/DP) : Monitors : Monitors : Nexus Technology UK, Colchester, Essex",
    "aspect_ratio": "16:9",
    "brightness": "300 cd/m²",
    "contrast_ratio": "1000:1",
    "ean": "4038986184373",
    "manufacturer": "AOC",
    "power_consumption": "0.5W",
    "pixel_pitch": "0.311mm",
    "model": "NEX-110149",
    "category": "Monitors",
    "description": "AOC m2870Vq 28\" Widescreen MVA LED Black Multimedia Monitor (1920 x 1080/5ms/VGA/DVI/HDMI/DP)",
    "response_time": "5ms",
    "screen_size": "28\"",
    "display_type": "MVA",
    "tilt_angle": "-5°/25°",
    "wall_mountable": "VESA 100mm x 100mm"
}