{
    "name": "Samsung S32D850T - MBE",
    "aspect_ratio": "16:9",
    "bluetooth": "No",
    "builtin_speakers": "No",
    "contrast_ratio": "Mega Contrast",
    "dimensions": "74.13 cm",
    "brightness": "300 cd/m²",
    "screen_size": "81.28 cm (32\")",
    "resolution": "2560 x 1440 pixels",
    "ethernet": "No",
    "height_adjustable": "Yes",
    "voltage": "100 - 240V",
    "led_indicators": "Yes",
    "manual": "Yes",
    "operating_temperature": "0 - 50 °C",
    "pivot": "Yes",
    "pixel_pitch": "0.27675 x 0.27675 mm",
    "plug_and_play": "Yes",
    "power_consumption": "60W",
    "response_time": "5 ms",
    "tilt_angle": "-5 - 20°",
    "weight": "9.4 kg",
    "wifi": "No"
}