{
    "name": "ASUS VW22ATL PROFESSIONAL RANGE  22 INCH LED  TN  1680 X 1050  5MS  MULTIMEDIA  VGA  DVI TILT  SWIVEL  PI - MBE",
    "builtin_camera": "No",
    "builtin_speakers": "Yes",
    "security_lock_slot": "Kensington",
    "contrast_ratio": "5000000:1",
    "dimensions": "51.395 cm",
    "brightness": "250 cd/m²",
    "screen_size": "55.9 cm",
    "resolution": "1680 x 1050 pixels",
    "certifications": "Yes",
    "hdcp_supported": "Yes",
    "height_adjustable": "Yes",
    "voltage": "100 - 240V",
    "audio_input": "Yes",
    "pivot": "Yes",
    "power_consumption": "33W",
    "manual": "Yes",
    "response_time": "5 ms",
    "tilt_angle": "-5 - 15°",
    "vga": "1",
    "weight": "6 kg"
}