{
    "name": "Benq Benq BL2700HT 9H.LCSLB.QBE Planet Computer.it",
    "dimensions": "62,3 cm",
    "builtin_speakers": "Si",
    "viewing_angle": "178°",
    "security_lock_slot": "Kensington",
    "bluetooth": "No",
    "certifications": "Si",
    "ethernet": "No",
    "display_colors": "16,77M",
    "vesa_mount_compatible": "100 x 100 mm",
    "screen_size": "68,58 cm (27\")",
    "pixel_pitch": "0,311 x 0,311 mm",
    "builtin_camera": "No",
    "swivel_angle": "Si",
    "hdcp_supported": "Si",
    "tilt_angle": "Si",
    "led_indicators": "Si",
    "wall_mountable": "Si",
    "weight": "8,2 kg",
    "pivot": "Si",
    "dvi": "Si",
    "contrast_ratio": "20000000:1",
    "height_adjustable": "12 cm",
    "resolution": "1920 x 1080 Pixels",
    "operating_system": "Si",
    "subwoofer": "No",
    "response_time": "4 ms",
    "display_type": "LED",
    "wifi": "No"
}