{
    "name": "VG2039M-LED - ViewSonic VG2039M-LED LED monitor - Xpcpro.com",
    "aspect_ratio": "16:9",
    "bluetooth": "N",
    "builtin_camera": "N",
    "builtin_speakers": "Y",
    "subwoofer": "Y",
    "security_lock_slot": "Kensington",
    "contrast_ratio": "20000000:1",
    "dimensions": "466 mm",
    "brightness": "250 cd/m²",
    "screen_size": "50.8 cm",
    "resolution": "1600 x 900 pixels",
    "certifications": "Silver",
    "ethernet": "N",
    "hdcp_supported": "N",
    "height_adjustable": "Y",
    "voltage": "100 - 240 V",
    "operating_system": "Y",
    "osd_languages": "Y",
    "operating_temperature": "0 - 40 °C",
    "power_consumption": "15 W",
    "manual": "Y",
    "response_time": "5 ms",
    "tilt_angle": "-5 - 20 °",
    "vga": "1",
    "weight": "2600 g",
    "wifi": "N"
}