{
    "name": "T52DEEU - Lenovo ThinkVision LT1421 - LED monitor - Xpcpro.com",
    "aspect_ratio": "16:9",
    "builtin_speakers": "No",
    "security_lock_slot": "Kensington",
    "dimensions": "335 mm",
    "brightness": "200 cd/m²",
    "screen_size": "355.6 mm (14 \")",
    "resolution": "1366 x 768 pixels",
    "osd_languages": "No",
    "operating_temperature": "-20 - 60 °C",
    "pixel_pitch": "0.227 x 0.227 mm",
    "power_consumption": "4.2 W",
    "response_time": "8 ms",
    "weight": "840 g"
}