{
    "name": "S26361-K1471-V140 - Fujitsu B19-7 LED LED monitor - Xpcpro.com",
    "aspect_ratio": "5:4",
    "bluetooth": "N",
    "builtin_camera": "N",
    "builtin_speakers": "N",
    "security_lock_slot": "Kensington",
    "contrast_ratio": "2000000:1",
    "dimensions": "414 mm",
    "brightness": "250 cd/m²",
    "screen_size": "48.3 cm",
    "resolution": "1280 x 1024 pixels",
    "display_surface": "Matt",
    "certifications": "Y",
    "ethernet": "N",
    "hdcp_supported": "Y",
    "height_adjustable": "Y",
    "voltage": "100 - 240 V",
    "led_indicators": "Y",
    "osd_languages": "Y",
    "operating_temperature": "5 - 35 °C",
    "pixel_pitch": "0.293 x 0.293 mm",
    "power_consumption": "17 W",
    "manual": "Y",
    "response_time": "8 ms",
    "tilt_angle": "-5 - 35 °",
    "vga": "1",
    "weight": "2850 g",
    "wifi": "N"
}