{
    "name": "Elo 1739l Open Frame Lcd Touchscreen Monitor 17\"   5 Wire Resistive   (e607940) | UK | Ebay Items | Best Deal Items | Auctions | Free Shipping | Goods | Services | Wholesales | Retail | Trade",
    "aspect_ratio": "5:4",
    "manufacturer": "Elo Touch Solutions, Inc",
    "brightness": "300 Nit",
    "condition": "Item type:",
    "contrast_ratio": "1,000:1",
    "country": "Category",
    "dimensions": "14.5\"",
    "voltage": "12 V DC",
    "warranty": "3 Year",
    "model": "1739L",
    "resolution": "1280 x 1024",
    "minimum_bid_count": "Maximum bid count:",
    "minimum_price": "Maximum price:",
    "power_consumption": "30 W",
    "payment_method": "Show Items:",
    "description": "Open-frame LCD Touchscreen Monitor",
    "response_time": "7.20 ms",
    "screen_size": "17\"",
    "refresh_rate": "75 Hz",
    "vesa_mount_compatible": "Yes",
    "vga": "Yes",
    "weight": "8.80 lb"
}