{
    "name": "3m Microtouch ( Black) M1700ss Touchscreen Lcd Monitor   17\"   (1191378227) | UK | Ebay Items | Best Deal Items | Auctions | Free Shipping | Goods | Services | Wholesales | Retail | Trade",
    "manufacturer": "3M",
    "brightness": "300 Nit",
    "condition": "Item type:",
    "contrast_ratio": "800:1",
    "country": "Category",
    "dimensions": "15.9\"",
    "dvi": "Yes",
    "voltage": "12 V DC",
    "warranty": "3 Year",
    "model": "M1700SS",
    "resolution": "1280 x 1024",
    "minimum_bid_count": "Maximum bid count:",
    "minimum_price": "Maximum price:",
    "payment_method": "Show Items:",
    "description": "LCD Touchscreen Monitor",
    "response_time": "9 ms",
    "screen_size": "17\"",
    "vga": "Yes",
    "weight": "18.96 lb"
}