{
    "name": "BenQ GL2760H 60Hz 27.0\" Monitor (GL2760H) - PCPartPicker Canada",
    "aspect_ratio": "16:9",
    "brightness": "300 cd/m²",
    "builtin_speakers": "No",
    "contrast_ratio": "DCR 12,000,000:1 (1000:1)",
    "display_colors": "16700000",
    "dvi": "1",
    "hdmi": "1",
    "backlight_technology": "Yes",
    "manufacturer": "BenQ",
    "part_number": "GL2760H",
    "refresh_rate": "60Hz",
    "response_time": "2 ms",
    "screen_size": "27\"",
    "vga": "1",
    "viewing_angle": "170° H x 160° V"
}